{
  "properties": {
    "activities": [
      {
        "type": "TridentNotebook",
        "typeProperties": {
          "notebookId": "3ef685a3-0550-8065-4a0f-775e2e0af3ef",
          "workspaceId": "00000000-0000-0000-0000-000000000000",
          "sessionTag": "LoadData"
        },
        "policy": {
          "timeout": "0.12:00:00",
          "retry": 0,
          "retryIntervalInSeconds": 30,
          "secureInput": false,
          "secureOutput": false
        },
        "name": "Load_Stage",
        "dependsOn": [
          {
            "activity": "Load_Raw",
            "dependencyConditions": [
              "Succeeded"
            ]
          }
        ]
      },
      {
        "type": "TridentNotebook",
        "typeProperties": {
          "notebookId": "001d2e2a-c133-9aa3-4b3e-8d70b8817cd9",
          "workspaceId": "00000000-0000-0000-0000-000000000000",
          "sessionTag": "LoadData"
        },
        "policy": {
          "timeout": "0.12:00:00",
          "retry": 0,
          "retryIntervalInSeconds": 30,
          "secureInput": false,
          "secureOutput": false
        },
        "name": "Load_Curated_DimCustomer",
        "dependsOn": [
          {
            "activity": "Load_Stage",
            "dependencyConditions": [
              "Succeeded"
            ]
          }
        ]
      },
      {
        "type": "TridentNotebook",
        "typeProperties": {
          "notebookId": "b387a08e-8370-82f7-46b4-ed0dd4681e73",
          "workspaceId": "00000000-0000-0000-0000-000000000000",
          "sessionTag": "LoadData"
        },
        "policy": {
          "timeout": "0.12:00:00",
          "retry": 0,
          "retryIntervalInSeconds": 30,
          "secureInput": false,
          "secureOutput": false
        },
        "name": "Load_Curated_DimProduct",
        "dependsOn": [
          {
            "activity": "Load_Stage",
            "dependencyConditions": [
              "Succeeded"
            ]
          }
        ]
      },
      {
        "type": "TridentNotebook",
        "typeProperties": {
          "notebookId": "e8622fa0-97f8-9859-4968-98974e0a47a3",
          "workspaceId": "00000000-0000-0000-0000-000000000000",
          "sessionTag": "LoadData"
        },
        "policy": {
          "timeout": "0.12:00:00",
          "retry": 0,
          "retryIntervalInSeconds": 30,
          "secureInput": false,
          "secureOutput": false
        },
        "name": "Load_Raw",
        "dependsOn": []
      },
      {
        "type": "TridentNotebook",
        "typeProperties": {
          "notebookId": "0405995f-16a9-82c3-4efa-40e680182808",
          "workspaceId": "00000000-0000-0000-0000-000000000000",
          "sessionTag": "LoadData"
        },
        "policy": {
          "timeout": "0.12:00:00",
          "retry": 0,
          "retryIntervalInSeconds": 30,
          "secureInput": false,
          "secureOutput": false
        },
        "name": "Load_Curated_FactSales",
        "dependsOn": [
          {
            "activity": "Load_Curated_DimCustomer",
            "dependencyConditions": [
              "Succeeded"
            ]
          },
          {
            "activity": "Load_Curated_DimProduct",
            "dependencyConditions": [
              "Succeeded"
            ]
          },
          {
            "activity": "Load_Curated_DimDate",
            "dependencyConditions": [
              "Succeeded"
            ]
          }
        ]
      },
      {
        "type": "TridentNotebook",
        "typeProperties": {
          "notebookId": "bc53d18e-f884-825b-4a56-953b4c50ace8",
          "workspaceId": "00000000-0000-0000-0000-000000000000",
          "sessionTag": "LoadData"
        },
        "policy": {
          "timeout": "0.12:00:00",
          "retry": 0,
          "retryIntervalInSeconds": 30,
          "secureInput": false,
          "secureOutput": false
        },
        "name": "Load_Curated_DimDate",
        "dependsOn": [
          {
            "activity": "Load_Stage",
            "dependencyConditions": [
              "Succeeded"
            ]
          }
        ]
      }
    ]
  }
}